khutbahmaker/__init__.py
khutbahmaker/webui.py
khutbahmaker-25.3.5.dist-info/licenses/LICENSE
khutbahmaker-25.3.5.dist-info/METADATA
khutbahmaker-25.3.5.dist-info/WHEEL
khutbahmaker-25.3.5.dist-info/top_level.txt
khutbahmaker-25.3.5.dist-info/RECORD
